<?xml version="1.0" encoding="UTF-8" standalone="yes"?>
<reference_data>
	<propulsion_system>
		<arcjet>
			<thruster>
					<type>arcjet</type>
					<name>Velarc</name>
					<thrust>0.04002</thrust>
					<c_e>4415</c_e>
					<massflow>9e-06</massflow>
					<mass>0.3</mass>
					<efficiency> 0.3178</efficiency>
					<propellant>NH3</propellant>
					<structure_mass> 0.94815</structure_mass>
					<source>IRS arcjet database</source>
			</thruster>
			<thruster>
					<type>arcjet</type>
					<name>ARTUS IM3</name>
					<thrust>0.1068829</thrust>
					<c_e>4836</c_e>
					<massflow>22.1e-06</massflow>
					<mass>0.732</mass>
					<efficiency> 0.324839</efficiency>
					<propellant>NH3</propellant>
					<structure_mass> 0.94815</structure_mass>
					<source>IRS arcjet database</source>
			</thruster>
			<thruster>
					<type>arcjet</type>
					<name>TALOS</name>
					<thrust>0.1025</thrust>
					<c_e>4767.442</c_e>
					<massflow>21.5e-06</massflow>
					<efficiency> 0.305414</efficiency>
					<propellant>NH3</propellant>
					<structure_mass> 0.94815</structure_mass>
					<source>IRS arcjet database</source>
			</thruster>
			<thruster>
					<type>arcjet</type>
					<name>ESEX -flight</name>
					<thrust>1.93</thrust>
					<c_e>7710.66</c_e>
					<massflow>0.000250302827514</massflow>
					<efficiency> 0.267</efficiency>
					<propellant>NH3</propellant>
					<structure_mass> 0.94815</structure_mass>
					<source>IRS arcjet database</source>
			</thruster>
			<thruster>
					<type>arcjet</type>
					<name>ESEX -IM</name>
					<thrust>2</thrust>
					<c_e>7848</c_e>
					<massflow>0.000254841997961</massflow>
					<efficiency> 0.299541984732824</efficiency>
					<propellant>NH3</propellant>
					<structure_mass> 0.94815</structure_mass>
					<source>IRS arcjet database</source>
			</thruster>
			<thruster>
					<type>arcjet</type>
					<name>Artur He</name>
					<thrust>0.270</thrust>
					<c_e>6136.35</c_e>
					<massflow>44e-06</massflow>
					<mass>0.455</mass>
					<efficiency> 0.702040</efficiency>
					<propellant>He</propellant>
					<structure_mass>0.493</structure_mass>
					<source>IRS arcjet database</source>
			</thruster>
			<thruster>
					<type>arcjet</type>
					<name>Artur He</name>
					<thrust>0.180</thrust>
					<c_e>4090.909302</c_e>
					<massflow>44e-06</massflow>
					<mass>0.455</mass>
					<efficiency> 0.73636</efficiency>
					<propellant>He</propellant>
					<structure_mass>0.493</structure_mass>
					<source>IRS arcjet database</source>
			</thruster>
			<thruster>
					<type>arcjet</type>
					<name>Velarc</name>
					<thrust>0.0345</thrust>
					<c_e>5886</c_e>
					<massflow>6e-06</massflow>
					<mass>0.3</mass>
					<efficiency> 0.7532</efficiency>
					<propellant>He</propellant>
					<structure_mass>0.493</structure_mass>
					<source>IRS arcjet database</source>
			</thruster>
			<ppu>
				<type>arcjet</type>
				<name>ATOS</name>
				<power>800</power>
				<mass>1.89</mass>
				<efficiency>0.92</efficiency>
				<source> Riehle, M.: ATOS - Arcjet Flugexperiment auf dem Amateurfunksatelliten AMSAT-P3-D, Final report, DARA FKZ TT 50 TT 9404, 1994</source>
			</ppu>
			<ppu>
				<type>arcjet</type>
				<name>MR-509</name>
				<power>1800</power>
				<mass>4.12</mass>
				<efficiency>0.90</efficiency>
				<source> Smith, R. D., Roberts, C. R., Aadland, R. S., Lichtin, D. A., Davies, K.: Flight
	qualification of the 1.8 kW MR-509 Hydrazine Arcjet System, IEPC-97-081, 25th International Electric Propulsion Conference, Cleveland Ohio. United States of America,1997, http://erps.spacegrant.org/uploads/images/images/iepc_articledownloAD1988-
	2007/1997index/7081.pdf</source>
			</ppu>
			<ppu>
				<type>arcjet</type>
				<name>MR-510</name>
				<power>2200</power>
				<mass>4.00</mass>
				<efficiency>0.907</efficiency>
				<source> Smith, R. D., Roberts, C. R., Aadland, R. S., Lichtin, D. A., Davies, K.: Flight
	qualification of the 1.8 kW MR-509 Hydrazine Arcjet System, IEPC-97-081, 25th International Electric Propulsion Conference, Cleveland Ohio. United States of America,1997, http://erps.spacegrant.org/uploads/images/images/iepc_articledownloAD1988-2007/1997index/7081.pdf</source>
			</ppu>
			<ppu>
				<type>arcjet</type>
				<name>MR-512</name>
				<power>1780</power>
				<mass>4.00</mass>
				<efficiency>0.91</efficiency>
				<source> MR-512, Enyclopedia Astronautica, Webpage, http://www.astronautix.com/m/mr-512.html, last accessed 24.10.2016</source>
			</ppu>
			<ppu>
				<type>arcjet</type>
				<name>ESEX</name>
				<power>30000</power>
				<mass>48.4</mass>
				<efficiency>0.95</efficiency>
				<source> https://erps.spacegrant.org/uploads/images/images/iepc_articledownload_1988-2007/1993index/IEPC1993-048.pdf</source>
			</ppu>
			<requiredsystems>
				<system>PPU</system>
				<system>Structure</system>
				<system>Propellant</system>
				<system>Tank</system>
			</requiredsystems>			
		</arcjet>
		<gridionthruster>
			<thruster>
					<type>gridionthruster</type>
					<name>Arclight</name>
					<thrust>0.012</thrust>
					<c_e>23544</c_e>
					<massflow>0.00000050968399592253</massflow>
					<mass>8</mass>
					<efficiency>0.35316</efficiency>
					<propellant>Xe</propellant>
					<structure_mass>12</structure_mass>
					<source> Ariane Group - ARCLIGHT
ELECTRIC PROPULSION SYSTEM DESIGNED FOR SMALL SATELLITES6, http://www.space-propulsion.com/brochures/electric-propulsion/arclight-electric-space-propulsion.pdf</source>
			</thruster>
			<thruster>
					<type>gridionthruster</type>
					<name>RIT 10 EVO mean</name>
					<thrust>0.015</thrust>
					<c_e>29430</c_e>
					<massflow>0.00000050968399592253</massflow>
					<mass>1.8</mass>
					<efficiency>0.507413793103448275</efficiency>
					<propellant>Xe</propellant>
					<structure_mass>5</structure_mass>
					<source> Ariane Group - http://www.space-propulsion.com/spacecraft-propulsion/propulsion-systems/electric-propulsion/images/rit-thruster-family-performance-data.jpg</source>
			</thruster>
			<thruster>
					<type>gridionthruster</type>
					<name>RIT 10 EVO min</name>
					<thrust>0.005</thrust>
					<c_e>18639</c_e>
					<mass>1.8</mass>
					<efficiency>0.3213662068</efficiency>
					<propellant>Xe</propellant>
					<structure_mass>5</structure_mass>
					<source> Ariane Group - http://www.space-propulsion.com/spacecraft-propulsion/propulsion-systems/electric-propulsion/images/rit-thruster-family-performance-data.jpg</source>
			</thruster>
			<thruster>
					<type>gridionthruster</type>
					<name>RIT 10 EVO max</name>
					<thrust>0.025</thrust>
					<c_e>31392</c_e>
					<mass>1.8</mass>
					<efficiency>0.516315789</efficiency>
					<propellant>Xe</propellant>
					<structure_mass>5</structure_mass>
					<source> Ariane Group - http://www.space-propulsion.com/spacecraft-propulsion/propulsion-systems/electric-propulsion/images/rit-thruster-family-performance-data.jpg</source>
			</thruster>
			<thruster>
					<type>gridionthruster</type>
					<name>RIT µX max</name>
					<thrust>0.0005</thrust>
					<c_e>29430</c_e>
					<mass>0.44</mass>
					<efficiency>0.516315789</efficiency>
					<propellant>Xe</propellant>
					<structure_mass>5</structure_mass>
					<source> Ariane Group - http://www.space-propulsion.com/spacecraft-propulsion/propulsion-systems/electric-propulsion/images/rit-thruster-family-performance-data.jpg</source>
			</thruster>
			<thruster>
					<type>gridionthruster</type>
					<name>RIT µX min</name>
					<thrust>0.00005</thrust>
					<c_e>2943</c_e>
					<mass>0.44</mass>
					<efficiency>0.14435415</efficiency>
					<propellant>Xe</propellant>
					<structure_mass>5</structure_mass>
					<source> Ariane Group - http://www.space-propulsion.com/spacecraft-propulsion/propulsion-systems/electric-propulsion/images/rit-thruster-family-performance-data.jpg</source>
			</thruster>
			<ppu>
					<type>gridionthruster</type>
					<name>Arclight PPU</name>
					<power>450</power>
					<efficiency>0.92</efficiency>
			</ppu>
			<requiredsystems>
				<system>PPU</system>
				<system>Structure</system>
				<system>Propellant</system>
				<system>Tank</system>
			</requiredsystems>
		</gridionthruster>
	</propulsion_system>
</reference_data>

